ethwlt_sdk
