Metadata-Version: 2.1
Name: ethwallet-sdk
Version: 0.0.2
Summary: SDK for ETH Wallet(以太坊钱包)
Home-page: https://github.com
Author: garder
Author-email: gaodelong01@163.com
License: UNKNOWN
Keywords: blockchain eth wallet
Platform: UNKNOWN
Classifier: Intended Audience :: Developers
Classifier: License :: OSI Approved :: MIT License
